<?xml version="1.0" encoding="windows-1251" ?>

<string_table>
	<string id="bar_room_upgrade_dialog_0">
		<text>Мне нужно пару ящиков в комнате.</text>
	</string>
	<string id="bar_room_upgrade_dialog_1">
		<text>Ящик около стола имеет кодовый замок, я хотел его убрать и, по неосторожности, захлопнул крышку. А вот сейф заклинило: надо бы починить дверцу. Давай договоримся за пару артефактов... Принесёшь мне "Слизняк", и я узнаю у одного сталкера код от замка на крышке ящика, за редкую "Слюду" починим дверцу сейфа. После этого сможешь складывать в них свои вещи. Как раз толстые металлические стенки сейфа будут сдерживать фонящие артефакты.</text>
	</string>
	<string id="bar_room_upgrade_dialog_2">
		<text>Держи "Слизняк" за ящик.</text>
	</string>
	<string id="bar_room_upgrade_dialog_2_1">
		<text>Значит так, код от замка следующий...</text>
	</string>
	<string id="bar_room_upgrade_dialog_3">
		<text>Есть "Слюда", почини сейф.</text>
	</string>
	<string id="bar_room_upgrade_dialog_3_1">
		<text>Петли смазали - частично помогло. Пришлось немного приложить грубой силы. Теперь дверца работает.</text>
	</string>
	<string id="bar_room_upgrade_dialog_4">
		<text>В другой раз.</text>
	</string>
	<string id="bar_room_upgrade_dialog_5">
		<text>Спасибо!</text>
	</string>
</string_table>