<?xml version="1.0" encoding="windows-1251" ?>
<game_dialogs>
	<dialog id="sidorovich_exo_upgrade_dialogs">
        <has_info>bun_antenna_off</has_info>
		<phrase_list>
            <phrase id="0">
                <text>sidorovich_exo_sprint_allowed_dialog_0</text>
                <next>1</next>
            </phrase>
			<phrase id="1">
                <text>sidorovich_exo_sprint_allowed_dialog_1</text>
                <next>2</next>
            </phrase>
			<phrase id="2">
                <text>sidorovich_exo_sprint_allowed_dialog_2</text>
                <next>3</next>
            </phrase>
			<phrase id="3">
                <text>sidorovich_exo_sprint_allowed_dialog_3</text>
                <next>41</next>
				<next>42</next>
				<next>5</next>
            </phrase>
			<phrase id="41">
				<precondition>outfit_upgrader.check_player_exo</precondition>
                <text>sidorovich_exo_sprint_allowed_dialog_4_1</text>
				<action>outfit_upgrader.exchange_exo</action>
                <next>6</next>
            </phrase>
			<phrase id="42">
				<precondition>outfit_upgrader.check_player_exo_m</precondition>
                <text>sidorovich_exo_sprint_allowed_dialog_4_2</text>
				<action>outfit_upgrader.exchange_exo_m1</action>
                <next>6</next>
            </phrase>
			<phrase id="5">
                <text>sidorovich_exo_sprint_allowed_dialog_5</text>
            </phrase>
			<phrase id="6">
                <text>sidorovich_exo_sprint_allowed_dialog_6</text>
            </phrase>
        </phrase_list>
    </dialog>
</game_dialogs>